adtr_client.py
adtr_client-0.0.4.dist-info/licenses/LICENSE
adtr_client-0.0.4.dist-info/METADATA
adtr_client-0.0.4.dist-info/WHEEL
adtr_client-0.0.4.dist-info/top_level.txt
adtr_client-0.0.4.dist-info/RECORD
